sorting_bboxes/__about__.py
sorting_bboxes/__init__.py
sorting_bboxes-0.1.0.dist-info/METADATA
sorting_bboxes-0.1.0.dist-info/WHEEL
sorting_bboxes-0.1.0.dist-info/licenses/LICENSE.txt
sorting_bboxes-0.1.0.dist-info/RECORD
